OnyxRequests/OnyxSessions.py
OnyxRequests/__init__.py
OnyxRequests-0.1.0.dist-info/METADATA
OnyxRequests-0.1.0.dist-info/WHEEL
OnyxRequests-0.1.0.dist-info/top_level.txt
OnyxRequests-0.1.0.dist-info/RECORD
